AUTHORS.rst
HISTORY.rst
LICENSE
MANIFEST.in
NOTICE
README.rst
csv2es.py
requirements.txt
setup.py
csv2es.egg-info/PKG-INFO
csv2es.egg-info/SOURCES.txt
csv2es.egg-info/dependency_links.txt
csv2es.egg-info/entry_points.txt
csv2es.egg-info/requires.txt
csv2es.egg-info/top_level.txt