Metadata-Version: 1.1
Name: csv2es
Version: 1.0.0
Summary: Bulk import a CSV or TSV into Elastic Search
Home-page: https://github.com/rholder/csv2es
Author: Ray Holder
Author-email: UNKNOWN
License: Apache 2.0
Keywords: elasticsearch es pyelasticsearch csv tsv bulk import kibana
Platform: UNKNOWN
Classifier: Intended Audience :: Developers
Classifier: Natural Language :: English
Classifier: License :: OSI Approved :: Apache Software License
Classifier: Programming Language :: Python
Classifier: Programming Language :: Python :: 2.6
Classifier: Programming Language :: Python :: 2.7
Classifier: Programming Language :: Python :: 3.3
Classifier: Programming Language :: Python :: 3.4
Classifier: Topic :: Internet
Classifier: Topic :: Utilities
